gh_notifier-0.0.1.dist-info/DESCRIPTION.rst
gh_notifier-0.0.1.dist-info/METADATA
gh_notifier-0.0.1.dist-info/RECORD
gh_notifier-0.0.1.dist-info/WHEEL
gh_notifier-0.0.1.dist-info/entry_points.txt
gh_notifier-0.0.1.dist-info/metadata.json
gh_notifier-0.0.1.dist-info/top_level.txt
ghnotifier/__init__.py
ghnotifier/handler.py
ghnotifier/main_cli.py
ghnotifier/notifier.py
ghnotifier/scrapper.py
ghnotifier/user.py
ghnotifier/tests/__init__.py
ghnotifier/tests/test_scrapper.py
