Metadata-Version: 2.0
Name: gh-notifier
Version: 0.0.1
Summary: A Desktop notifier for all your social GitHub notifications
Home-page: https://github.com/kshitij10496/gh-notifier
Author: Kshitij Saraogi
Author-email: KshitijSaraogi@gmail.com
License: MIT
Keywords: github
Platform: UNKNOWN
Classifier: Development Status :: 3 - Alpha
Classifier: Intended Audience :: Developers
Classifier: License :: OSI Approved :: MIT License
Classifier: Programming Language :: Python :: 3
Requires-Dist: requests
Requires-Dist: PyGitHub
Requires-Dist: bs4
